threadedproxyobject/README.MD
threadedproxyobject/__init__.py
threadedproxyobject/requirements.txt
threadedproxyobject/thirdparty.json
threadedproxyobject-0.10.dist-info/LICENSE.rst
threadedproxyobject-0.10.dist-info/METADATA
threadedproxyobject-0.10.dist-info/WHEEL
threadedproxyobject-0.10.dist-info/top_level.txt
threadedproxyobject-0.10.dist-info/RECORD
