Metadata-Version: 2.1
Name: threadedproxyobject
Version: 0.10
Summary: Threaded Proxy Object
Home-page: https://github.com/hansalemaos/threadedproxyobject
Author: Johannes Fischer
Author-email: aulasparticularesdealemaosp@gmail.com
License: MIT
Keywords: threads,ProxyObject
Classifier: Development Status :: 4 - Beta
Classifier: Programming Language :: Python :: 3 :: Only
Classifier: Programming Language :: Python :: 3.10
Classifier: Topic :: Software Development :: Libraries :: Python Modules
Classifier: Topic :: Utilities
License-File: LICENSE.rst
